rgtest/__init__.py
rgtest/rg.py
rgtest-1.0.dist-info/LICENSE.txt
rgtest-1.0.dist-info/METADATA
rgtest-1.0.dist-info/WHEEL
rgtest-1.0.dist-info/top_level.txt
rgtest-1.0.dist-info/RECORD
